tokkit/__init__.py
tokkit/tokenizer.cpython-312-i386-linux-musl.so
tokkit/tokenizer.pyi
tokkit/bindings/__init__.py
tokkit/bindings/tokenizer.cpp
tokkit/bindings/tokenizer.pxd
tokkit/bindings/tokenizer.pyx
tokkit/cpp/data.cpp
tokkit/cpp/data.h
tokkit/cpp/dtypes.h
tokkit/cpp/run.cpp
tokkit/cpp/tokenizer.cpp
tokkit/cpp/tokenizer.h
tokkit/cpp/utils.cpp
tokkit/cpp/utils.h
tokkit.libs/libgcc_s-887de51c.so.1
tokkit.libs/libstdc++-d6415257.so.6.0.33
tokkit-0.0.5.dist-info/METADATA
tokkit-0.0.5.dist-info/WHEEL
tokkit-0.0.5.dist-info/top_level.txt
tokkit-0.0.5.dist-info/RECORD
tokkit-0.0.5.dist-info/licenses/LICENSE
