Metadata-Version: 2.4
Name: tokkit
Version: 0.0.5
Summary: This is description
Author-email: Nishant Baheti <nishantbaheti.it19@gmail.com>
License: MIT License
Project-URL: Homepage, https://github.com/nishantbaheti/tokkit
Project-URL: Bug Reports, https://github.com/nishantbaheti/tokkit/issues
Project-URL: Source, https://github.com/nishantbaheti/tokkit/
Keywords: tokkit
Classifier: Intended Audience :: Developers
Classifier: Topic :: Software Development :: Build Tools
Classifier: Programming Language :: Python :: 3
Classifier: Programming Language :: Python :: 3.10
Classifier: Programming Language :: Python :: 3 :: Only
Classifier: Intended Audience :: Science/Research
Classifier: Intended Audience :: Developers
Requires-Python: >=3.10
License-File: LICENSE
Requires-Dist: Cython==3.0.12
Provides-Extra: dev
Requires-Dist: tokkit; extra == "dev"
Requires-Dist: pylint==3.0.3; extra == "dev"
Requires-Dist: pip-tools==7.3.0; extra == "dev"
Requires-Dist: black==25.1.0; extra == "dev"
Provides-Extra: test
Requires-Dist: tokkit[dev]; extra == "test"
Dynamic: license-file
